odoo/addons/apps_download/README.rst
odoo/addons/apps_download/__init__.py
odoo/addons/apps_download/__manifest__.py
odoo/addons/apps_download/data/cron_scheduler.xml
odoo/addons/apps_download/demo/product_template_demo.xml
odoo/addons/apps_download/i18n/apps_download.pot
odoo/addons/apps_download/i18n/es.po
odoo/addons/apps_download/i18n/fr.po
odoo/addons/apps_download/i18n/it.po
odoo/addons/apps_download/i18n/pt_BR.po
odoo/addons/apps_download/models/__init__.py
odoo/addons/apps_download/models/product_product.py
odoo/addons/apps_download/readme/CONTRIBUTORS.rst
odoo/addons/apps_download/readme/DESCRIPTION.rst
odoo/addons/apps_download/readme/ROADMAP.rst
odoo/addons/apps_download/static/description/icon.png
odoo/addons/apps_download/static/description/index.html
odoo/addons/apps_download/tests/__init__.py
odoo/addons/apps_download/tests/test_app_download.py
odoo/addons/apps_download/tests/test_modules/broken_lint/__init__.py
odoo/addons/apps_download/tests/test_modules/broken_lint/__manifest__.py
odoo/addons/apps_download/tests/test_modules/broken_lint/case_deprecated.py
odoo/addons/apps_download/tests/test_modules/broken_lint/case_fields.py
odoo/addons/apps_download/tests/test_modules/broken_lint/case_import.py
odoo/addons/apps_download/tests/test_modules/broken_lint/eval_referenced.py
odoo/addons/apps_download/tests/test_modules/second_module/__init__.py
odoo/addons/apps_download/tests/test_modules/second_module/__manifest__.py
odoo/addons/apps_download/tests/test_modules/test_module/README.rst
odoo/addons/apps_download/tests/test_modules/test_module/__init__.py
odoo/addons/apps_download/tests/test_modules/test_module/__manifest__.py
odoo/addons/apps_download/tests/test_modules/test_module/dummy_model.py
odoo/addons/apps_download/tests/test_modules/test_module/doc/index.rst
odoo/addons/apps_download/tests/test_modules/test_module/security/ir.model.access.csv
odoo/addons/apps_download/tests/test_modules/test_module/static/description/icon.png
odoo12_addon_apps_download-12.0.1.0.0.99.dev13.dist-info/METADATA
odoo12_addon_apps_download-12.0.1.0.0.99.dev13.dist-info/WHEEL
odoo12_addon_apps_download-12.0.1.0.0.99.dev13.dist-info/top_level.txt
odoo12_addon_apps_download-12.0.1.0.0.99.dev13.dist-info/RECORD
