Metadata-Version: 2.1
Name: odoo12-addon-apps-download
Version: 12.0.1.0.0.99.dev13
Summary: Product Download for Appstore
Home-page: https://github.com/OCA/apps-store
Author: BizzAppDev, AgentERP, Elico Corp, Odoo Community Association (OCA)
Author-email: support@odoo-community.org
License: AGPL-3
Platform: UNKNOWN
Classifier: Programming Language :: Python
Classifier: Framework :: Odoo
Classifier: Framework :: Odoo :: 12.0
Classifier: License :: OSI Approved :: GNU Affero General Public License v3
Requires-Python: >=3.5
Requires-Dist: odoo12-addon-apps-product-creator
Requires-Dist: odoo12-addon-github-connector-odoo
Requires-Dist: odoo <12.1dev,>=12.0a
